{
  "parent": "minecraft:recipes/root",
  "rewards": {
    "recipes": [
      "alchemia:mageberry_crushed_from_ingredient"
    ]
  },
  "criteria": {
    "has_Mageberry_ingredient": {
      "trigger": "minecraft:inventory_changed",
      "conditions": {
        "items": [
          {
            "items": [
              "alchemia:herb_mageberry_crushed"
            ]
          }
        ]
      }
    },
    "has_the_recipe": {
      "trigger": "minecraft:recipe_unlocked",
      "conditions": {
        "recipe": "alchemia:mageberry_crushed_from_ingredient"
      }
    }
  },
  "requirements": [
    [
      "has_Mageberry_ingredient",
      "has_the_recipe"
    ]
  ]
}